[
  {
    "name": "Services - Service plan datagrid with bulk actions",
    "gid": "1211631360190563",
    "status": "on_track",
    "stage": "Development",
    "jira_link": "CBP-3066",
    "milestones": {}
  },
  {
    "name": "Notes - Notes datagrid",
    "gid": "1209963394727039",
    "status": "on_track",
    "stage": "GA",
    "jira_link": "CBP-2736",
    "milestones": {"qa_start": "2026-03-20", "uat_start": "2026-04-03"}
  },
  {
    "name": "Service Plan - Bulk Services section",
    "gid": "1211631356870657",
    "status": "on_track",
    "stage": "Beta",
    "jira_link": "CBP-2992",
    "milestones": {"qa_start": "2026-02-26", "uat_start": "2026-03-12", "beta_start": "2026-03-18"}
  }
]