[
    {
        "name": "Notes - Notes datagrid",
        "gid": "1208822149019495",
        "permalink_url": "https://app.asana.com/0/1123317448830974/1208822149019495",
        "current_status_update": {
            "status_type": "on_track"
        },
        "custom_fields": [
            {
                "gid": "1208820967756795",
                "name": "Team",
                "enum_value": {
                    "gid": "1208820967756799",
                    "name": "Platform"
                }
            },
            {
                "gid": "1208818005809198",
                "name": "JIRA Link",
                "display_value": "https://casecommons.atlassian.net/browse/CBP-2736"
            },
            {
                "gid": "1208822149019495",
                "name": "Stage",
                "display_value": "GA"
            }
        ]
    }
]